calcifer/__init__.py
calcifer/asts.py
calcifer/definitions.py
calcifer/monads.py
calcifer/operators.py
calcifer/partial.py
calcifer/policy.py
calcifer/tree.py
calcifer/utils.py
calcifer/contexts/__init__.py
calcifer/contexts/base.py
calcifer/contexts/context.py
calcifer/contexts/policies.py
calcifer-0.0.0.dist-info/DESCRIPTION.rst
calcifer-0.0.0.dist-info/METADATA
calcifer-0.0.0.dist-info/metadata.json
calcifer-0.0.0.dist-info/RECORD
calcifer-0.0.0.dist-info/top_level.txt
calcifer-0.0.0.dist-info/WHEEL
