Metadata-Version: 2.0
Name: calcifer
Version: 0.0.0
Summary: A Python based policy framework.
Home-page: https://github.com/DramaFever/calcifer
Author: DramaFever
Author-email: admin@dramafever.com
License: UNKNOWN
Platform: UNKNOWN
Classifier: Development Status :: 1 - Planning
Classifier: Intended Audience :: Developers
Classifier: License :: Other/Proprietary License
Classifier: Natural Language :: English
Classifier: Operating System :: OS Independent
Classifier: Programming Language :: Python :: 2
Classifier: Programming Language :: Python :: 2.7
Classifier: Programming Language :: Python :: 3
Classifier: Programming Language :: Python :: 3.4
Requires-Dist: jsonpointer (==1.10)
Requires-Dist: PyMonad (==1.3)
